qosst_hal/__init__.py
qosst_hal/adc.py
qosst_hal/amperemeter.py
qosst_hal/base.py
qosst_hal/dac.py
qosst_hal/dacadc.py
qosst_hal/exceptions.py
qosst_hal/laser.py
qosst_hal/modulator_bias_control.py
qosst_hal/polarisation_controller.py
qosst_hal/powermeter.py
qosst_hal/powersupply.py
qosst_hal/py.typed
qosst_hal/switch.py
qosst_hal/utils.py
qosst_hal/voa.py
qosst_hal/voltmeter.py
qosst_hal-0.10.0.dist-info/LICENSE
qosst_hal-0.10.0.dist-info/METADATA
qosst_hal-0.10.0.dist-info/WHEEL
qosst_hal-0.10.0.dist-info/RECORD
